LICENSE
MANIFEST.in
README
setup.py
Scripts/rsMap3D
Scripts/rsMap3D.bat
rsMap3D/__init__.py
rsMap3D/constants.py
rsMap3D/rsmEdit.py
rsMap3D.egg-info/PKG-INFO
rsMap3D.egg-info/SOURCES.txt
rsMap3D.egg-info/dependency_links.txt
rsMap3D.egg-info/requires.txt
rsMap3D.egg-info/top_level.txt
rsMap3D/anglecalcexamples/__init__.py
rsMap3D/anglecalcexamples/copycolumn.py
rsMap3D/anglecalcexamples/sumgammamu.py
rsMap3D/config/__init__.py
rsMap3D/config/rsmap3dconfig.py
rsMap3D/config/rsmap3dconfigparser.py
rsMap3D/config/rsmap3dlogging.py
rsMap3D/datasource/AbstractXrayUtilitiesDataSource.py
rsMap3D/datasource/DetectorGeometryForXrayutilitiesReader.py
rsMap3D/datasource/InstForXrayutilitiesReader.py
rsMap3D/datasource/Sector33SpecDataSource.py
rsMap3D/datasource/__init__.py
rsMap3D/datasource/abstractDataSource.py
rsMap3D/datasource/pilatusbadpixelfile.py
rsMap3D/datasource/s1highenergydiffractionds.py
rsMap3D/datasource/s1highenergydiffractionds_MPI2.py
rsMap3D/datasource/s1highenergydiffractionds_mpi.py
rsMap3D/datasource/s1mpiclient.py
rsMap3D/datasource/sector34nexusescansource.py
rsMap3D/datasource/specxmldrivendatasource.py
rsMap3D/datasource/xpcsspecdatasource.py
rsMap3D/datasource/DetectorGeometry/__init__.py
rsMap3D/datasource/DetectorGeometry/detectorgeometrybase.py
rsMap3D/datasource/DetectorGeometry/detectorgeometryforescan.py
rsMap3D/exception/__init__.py
rsMap3D/exception/rsmap3dexception.py
rsMap3D/gui/__init__.py
rsMap3D/gui/dataextentview.py
rsMap3D/gui/datarange.py
rsMap3D/gui/processscans.py
rsMap3D/gui/qtsignalstrings.py
rsMap3D/gui/rsm3dcommonstrings.py
rsMap3D/gui/rsmap3dsignals.py
rsMap3D/gui/scanform.py
rsMap3D/gui/input/__init__.py
rsMap3D/gui/input/abstractfileview.py
rsMap3D/gui/input/abstractimageperfileview.py
rsMap3D/gui/input/fileinputcontroller.py
rsMap3D/gui/input/s1highenergydiffractionform.py
rsMap3D/gui/input/s33specscanfileform.py
rsMap3D/gui/input/s34hdfescanfileform.py
rsMap3D/gui/input/specxmldrivenfileform.py
rsMap3D/gui/input/usescommonoutputtype.py
rsMap3D/gui/input/usesxmldetectorconfig.py
rsMap3D/gui/input/usesxmlinstconfig.py
rsMap3D/gui/input/xpcsspecscanfileform.py
