Metadata-Version: 1.0
Name: rsMap3D
Version: 1.2.1
Summary: Python Program to map xray diffraction data into reciprocal space map
Home-page: https://confluence.aps.anl.gov/display/RSM/SSG_000116+Reciprocal+Space+Mapping
Author: John Hammonds, Christian Schleputz
Author-email: JPHammonds@anl.gov
License: See LICENSE File
Platform: any
